{
  "00001-testicular-torsion": {
    "slidesGeneratedAt": "2026-06-18T18:15:43.070Z",
    "postedAt": "2026-06-18T19:29:57.520Z",
    "igMediaId": "18084535706548047"
  },
  "00002-acute-abdomen-peritonitis": {
    "slidesGeneratedAt": "2026-06-18T18:40:33.202Z",
    "postedAt": "2026-06-19T17:01:14.311Z",
    "igMediaId": "18177812071409078"
  },
  "00003-inguinal-hernia-direct-indirect": {
    "slidesGeneratedAt": "2026-06-18T18:41:53.201Z",
    "postedAt": "2026-06-20T16:01:07.039Z",
    "igMediaId": "18025173077839089"
  },
  "00004-hernia-strangulation-traps": {
    "slidesGeneratedAt": "2026-06-18T18:43:09.641Z",
    "postedAt": "2026-06-21T16:01:21.129Z",
    "igMediaId": "18117096595644329"
  },
  "00005-ventral-hernias": {
    "slidesGeneratedAt": "2026-06-18T18:44:42.203Z",
    "postedAt": "2026-06-22T16:01:51.123Z",
    "igMediaId": "18065562605705113"
  },
  "00006-varicocele": {
    "slidesGeneratedAt": "2026-06-18T18:53:50.513Z",
    "postedAt": "2026-06-23T16:01:10.718Z",
    "igMediaId": "17916713859404837"
  },
  "00007-shingles-zoster": {
    "slidesGeneratedAt": "2026-06-18T19:00:09.042Z",
    "postedAt": "2026-06-24T16:01:06.720Z",
    "igMediaId": "18146997703511296"
  },
  "00008-fibroadenoma-breast-mouse": {
    "slidesGeneratedAt": "2026-07-10T09:43:39.423Z",
    "postedAt": "2026-07-10T16:01:49.042Z",
    "igMediaId": "18200949508367849"
  },
  "00009-triple-assessment-breast-lump": {
    "slidesGeneratedAt": "2026-07-10T09:49:27.708Z",
    "postedAt": "2026-07-11T16:01:21.724Z",
    "igMediaId": "17977225287025069"
  },
  "00010-duct-ectasia-vs-periductal-mastitis": {
    "slidesGeneratedAt": "2026-07-10T09:55:40.485Z",
    "postedAt": "2026-07-12T16:01:22.393Z",
    "igMediaId": "17894775339552345"
  },
  "00011-bloody-nipple-discharge-decoded": {
    "slidesGeneratedAt": "2026-07-10T10:01:24.559Z",
    "postedAt": "2026-07-13T16:01:42.676Z",
    "igMediaId": "18145805044521733"
  },
  "00012-gynaecomastia-drug-culprits": {
    "slidesGeneratedAt": "2026-07-10T10:07:06.795Z",
    "postedAt": "2026-07-14T16:02:01.244Z",
    "igMediaId": "18458212249118124"
  },
  "00013-breast-abscess-48-hour-rule": {
    "slidesGeneratedAt": "2026-07-10T10:12:29.960Z",
    "postedAt": "2026-07-15T16:01:19.611Z",
    "igMediaId": "18118145569888647"
  },
  "00014-benign-breast-disease-risk-ladder": {
    "slidesGeneratedAt": "2026-07-10T10:18:27.998Z",
    "postedAt": "2026-07-16T16:01:09.148Z",
    "igMediaId": "18109874240085911"
  }
}
